codinasion_tools/__init__.py
codinasion_tools/add_two_numbers.py
codinasion_tools/convert_binary_to_decimal.py
codinasion_tools/convert_binary_to_hexadecimal.py
codinasion_tools/convert_binary_to_octal.py
codinasion_tools/convert_celsius_to_fahrenheit.py
codinasion_tools/convert_centimeters_to_feet.py
codinasion_tools/convert_centimeters_to_inches.py
codinasion_tools/convert_days_to_hours.py
codinasion_tools/convert_days_to_minutes.py
codinasion_tools/convert_days_to_seconds.py
codinasion_tools/convert_decimal_to_binary.py
codinasion_tools/convert_decimal_to_hexadecimal.py
codinasion_tools/convert_decimal_to_octal.py
codinasion_tools/convert_hexadecimal_to_binary.py
codinasion_tools/convert_hexadecimal_to_decimal.py
codinasion_tools/convert_hexadecimal_to_octal.py
codinasion_tools/convert_octal_to_binary.py
codinasion_tools/convert_octal_to_decimal.py
codinasion_tools/convert_octal_to_hexadecimal.py
codinasion_tools/format_to_camelcase.py
codinasion_tools/format_to_constantcase.py
codinasion_tools/format_to_dotcase.py
codinasion_tools/format_to_kebabcase.py
codinasion_tools/format_to_pascalcase.py
codinasion_tools/format_to_pathcase.py
codinasion_tools/format_to_snakecase.py
codinasion_tools/format_to_titlecase.py
codinasion_tools/substract_two_numbers.py
codinasion_tools-0.1.1.dist-info/METADATA
codinasion_tools-0.1.1.dist-info/WHEEL
codinasion_tools-0.1.1.dist-info/top_level.txt
codinasion_tools-0.1.1.dist-info/RECORD
